pyramid_is_live.py
pyramid_is_live-0.1.0.post4.dist-info/METADATA
pyramid_is_live-0.1.0.post4.dist-info/RECORD
pyramid_is_live-0.1.0.post4.dist-info/WHEEL
pyramid_is_live-0.1.0.post4.dist-info/top_level.txt
