Metadata-Version: 2.1
Name: pyramid-is-live
Version: 0.1.0.post4
Summary: Add is_live to your Pyramid requests
Home-page: UNKNOWN
License: MIT
Platform: UNKNOWN
Classifier: Intended Audience :: Developers
Classifier: Programming Language :: Python
Classifier: Programming Language :: Python :: 2.7
Classifier: Programming Language :: Python :: 3
Classifier: Programming Language :: Python :: 3.6
Classifier: Framework :: Pyramid
Classifier: License :: OSI Approved :: MIT License
Requires-Dist: pyramid
